{
    "homepage": "https://github.com/chaojimct/clipboardx",
    "description": "轻量级 Windows 剪贴板历史",
    "version": "1.6.3",
    "license": "MIT",
    "url": "https://github.com/chaojimct/clipboardx/releases/download/v1.6.3/ClipboardX-clipboard-1.6.3-win-x64-self-contained.zip",
    "hash": "2f0f175f54dfd114d0ce8ca82559a6be0787c03675624bcb75b0a58e9c440da2",
    "shortcuts": [
        [
            "ClipboardX-clipboard",
            "ClipboardX"
        ]
    ],
    "persist": "Data",
    "checkver": "github",
    "autoupdate": {
        "url": "https://github.com/chaojimct/clipboardx/releases/download/v$version/ClipboardX-clipboard-$version-win-x64-self-contained.zip"
    }
}
