{
    "version": "1.22.1",
    "description": "使用图形化的 Scrcpy 显示和控制您的 Android 设备",
    "homepage": "https://github.com/viarotel-org/escrcpy",
    "license": "MIT",
    "architecture": {
        "64bit": {
            "url": "https://github.com/viarotel-org/escrcpy/releases/download/v1.22.1/Escrcpy-1.22.1-win-x64.zip",
            "hash": "0bcb2f40e3c1c48a2af389ec5256e57a7aa48a6ce44bbccc5f4220df044dd177"
        },
        "arm64": {
            "url": "https://github.com/viarotel-org/escrcpy/releases/download/v1.22.1/Escrcpy-1.22.1-win-arm64.zip",
            "hash": "66929de4eeb409625afe7bdf7fe0aced91cf6bc5e21d3d8ae37b8896eea100f2"
        }
    },
    "shortcuts": [
        [
            "Escrcpy.exe",
            "Escrcpy",
            "--user-data-dir=\"$dir\\User Data\""
        ]
    ],
    "persist": "User Data",
    "checkver": "github",
    "autoupdate": {
        "architecture": {
            "64bit": {
                "url": "https://github.com/viarotel-org/escrcpy/releases/download/v$version/Escrcpy-$version-win-x64.zip"
            },
            "arm64": {
                "url": "https://github.com/viarotel-org/escrcpy/releases/download/v$version/Escrcpy-$version-win-arm64.zip"
            }
        }
    }
}
