{
    "homepage": "https://github.com/skydevil88/XboxDownload",
    "description": "Xbox下载助手",
    "version": "2022-07-31",
    "license": "Unlicense",
    "url": "https://github.com/skydevil88/XboxDownload/releases/download/2022-07-31/XboxDownload.zip",
    "hash": "e986d56dd86376e80194c8ae6b0b4ef33d505f959478ab5b4fb34da8e054f220",
    "extract_dir": "Xbox下载助手",
    "shortcuts": [
        [
            "XboxDownload.exe",
            "Xbox下载助手"
        ]
    ],
    "checkver": {
        "url": "https://github.com/skydevil88/XboxDownload/releases/latest",
        "regex": "<title>Release ([\\d.]+-[\\d.]+-[\\d.]+)"
    },
    "autoupdate": {
        "url": "https://github.com/skydevil88/XboxDownload/releases/download/$version/XboxDownload.zip"
    }
}
